{
  "symbol":"BCE.TO",
  "dividends": [
  {"date": "03/14/18","amount":0.755},
  {"date": "12/14/17","amount":0.718},
  {"date": "09/14/17","amount":0.718},
  {"date": "06/13/17","amount":0.718},
  {"date": "03/13/17","amount":0.718},
  {"date": "12/13/16","amount":0.683},
  {"date": "09/13/16","amount":0.683},
  {"date": "06/13/16","amount":0.683},
  {"date": "03/11/16","amount":0.683},
  {"date": "12/11/15","amount":0.650},
  {"date": "09/11/15","amount":0.650},
  {"date": "06/11/15","amount":0.650},
  {"date": "03/12/15","amount":0.650},
  {"date": "12/11/14","amount":0.618},
  {"date": "09/11/14","amount":0.618},
  {"date": "06/12/14","amount":0.618},
  {"date": "03/12/14","amount":0.618},
  {"date": "12/12/13","amount":0.583},
  {"date": "09/12/13","amount":0.583},
  {"date": "06/12/13","amount":0.583},
  {"date": "03/13/13","amount":0.583},
  {"date": "12/12/12","amount":0.568},
  {"date": "09/12/12","amount":0.568},
  {"date": "06/13/12","amount":0.543},
  {"date": "03/13/12","amount":0.543},
  {"date": "12/13/11","amount":0.518},
  {"date": "09/13/11","amount":0.518},
  {"date": "06/13/11","amount":0.518},
  {"date": "03/11/11","amount":0.493},
  {"date": "12/13/10","amount":0.458},
  {"date": "09/13/10","amount":0.458},
  {"date": "06/11/10","amount":0.435},
  {"date": "03/11/10","amount":0.435},
  {"date": "12/11/09","amount":0.405},
  {"date": "09/11/09","amount":0.405},
  {"date": "06/11/09","amount":0.385},
  {"date": "03/12/09","amount":0.385},
  {"date": "12/19/08","amount":0.365},
  {"date": "03/12/08","amount":0.365},
  {"date": "12/12/07","amount":0.365},
  {"date": "09/12/07","amount":0.365},
  {"date": "06/13/07","amount":0.365},
  {"date": "03/13/07","amount":0.365},
  {"date": "12/13/06","amount":0.330},
  {"date": "09/13/06","amount":0.330},
  {"date": "06/13/06","amount":0.330},
  {"date": "03/13/06","amount":0.330},
  {"date": "12/13/05","amount":0.330},
  {"date": "09/13/05","amount":0.330},
  {"date": "06/13/05","amount":0.330},
  {"date": "03/11/05","amount":0.330},
  {"date": "12/13/04","amount":0.300},
  {"date": "09/13/04","amount":0.300},
  {"date": "03/11/04","amount":0.300},
  {"date": "12/11/03","amount":0.300},
  {"date": "09/11/03","amount":0.300},
  {"date": "06/12/03","amount":0.300},
  {"date": "03/13/03","amount":0.300},
  {"date": "12/11/02","amount":0.300},
  {"date": "09/11/02","amount":0.300},
  {"date": "06/12/02","amount":0.300},
  {"date": "03/13/02","amount":0.300},
  {"date": "12/12/01","amount":0.300},
  {"date": "06/13/01","amount":0.300},
  {"date": "03/13/01","amount":0.300},
  {"date": "12/13/00","amount":0.300},
  {"date": "09/13/00","amount":0.300},
  {"date": "06/13/00","amount":0.300},
  {"date": "03/13/00","amount":0.340},
  {"date": "12/13/99","amount":0.340},
  {"date": "09/13/99","amount":0.340},
  {"date": "06/11/99","amount":0.340},
  {"date": "03/11/99","amount":0.340},
  {"date": "12/11/98","amount":0.340},
  {"date": "09/11/98","amount":0.340},
  {"date": "06/11/98","amount":0.340},
  {"date": "03/11/98","amount":0.340},
  {"date": "12/11/97","amount":0.340},
  {"date": "09/29/97","amount":0.330},
  {"date": "09/11/97","amount":0.340},
  {"date": "06/11/97","amount":0.340},
  {"date": "03/12/97","amount":0.340},
  {"date": "12/11/96","amount":0.340},
  {"date": "09/11/96","amount":0.340},
  {"date": "06/12/96","amount":0.340}
  ]
}
